.gitignore
README.md
example.py
setup.py
pagerator/__init__.py
pagerator/tests.py
pagerator.egg-info/PKG-INFO
pagerator.egg-info/SOURCES.txt
pagerator.egg-info/dependency_links.txt
pagerator.egg-info/top_level.txt