Metadata-Version: 1.0
Name: pagerator
Version: 0.1.1
Summary: A helper to build iterables when you need to fetch results already divided into the pages.
Home-page: http://github.com/svetlyak40wt/pagerator/
Author: Alexander Artemenko
Author-email: svetlyak.40wt@gmail.com
License: New BSD License
Keywords: helper utility
Platform: UNKNOWN
Classifier: Development Status :: 2 - Pre-Alpha
Classifier: Intended Audience :: Developers
Classifier: License :: OSI Approved :: BSD License
Classifier: Programming Language :: Python
Classifier: Topic :: Software Development :: Libraries :: Python Modules
